[
{
  "directory": "e:\\Projects\\Cpp\\TensorRT-YOLO",
  "arguments": ["C:\\Program Files\\NVIDIA GPU Computing Toolkit\\CUDA\\v11.7\\bin\\nvcc.exe", "-c", "-O3", "-Ie:\\Projects\\Cpp\\TensorRT-YOLO\\include", "-I\"C:\\Program Files\\NVIDIA GPU Computing Toolkit\\TensorRT\\v8.6.1.6\\include\"", "-I\"C:\\Program Files\\NVIDIA GPU Computing Toolkit\\CUDA\\v11.7\\include\"", "--std", "c++17", "-DENABLE_DEPLOY_BUILDING_DLL", "-ID:\\laugh\\Program\\Xmake\\.xmake\\packages\\o\\opencv\\4.8.0\\69684747aed04b64833b165b90454f36\\include", "-m64", "-rdc=true", "-gencode", "arch=compute_75,code=sm_75", "-o", "build\\.objs\\deploy\\windows\\x64\\release\\source\\deploy\\vision\\warp_affine.cu.obj", "source\\deploy\\vision\\warp_affine.cu", "-imsvc", "D:\\Windows Kits\\10\\Include\\10.0.22621.0\\cppwinrt", "-imsvc", "D:\\Windows Kits\\10\\Include\\10.0.22621.0\\shared", "-imsvc", "D:\\Windows Kits\\10\\Include\\10.0.22621.0\\ucrt", "-imsvc", "D:\\Windows Kits\\10\\Include\\10.0.22621.0\\um", "-imsvc", "D:\\Windows Kits\\10\\Include\\10.0.22621.0\\winrt"],
  "file": "source\\deploy\\vision\\warp_affine.cu"
},
{
  "directory": "e:\\Projects\\Cpp\\TensorRT-YOLO",
  "arguments": ["D:\\laugh\\Program\\Microsoft Visual Studio\\2022\\Professional\\VC\\Tools\\MSVC\\14.38.33130\\bin\\HostX64\\x64\\cl.exe", "/c", "/nologo", "/O2", "/fp:fast", "/std:c++17", "/Ie:\\Projects\\Cpp\\TensorRT-YOLO\\include", "/IC:\\Program Files\\NVIDIA GPU Computing Toolkit\\TensorRT\\v8.6.1.6\\include", "/IC:\\Program Files\\NVIDIA GPU Computing Toolkit\\CUDA\\v11.7\\include", "/DENABLE_DEPLOY_BUILDING_DLL", "/EHsc", "/ID:\\laugh\\Program\\Xmake\\.xmake\\packages\\o\\opencv\\4.8.0\\69684747aed04b64833b165b90454f36\\include", "/DNDEBUG", "/Fobuild\\.objs\\deploy\\windows\\x64\\release\\source\\deploy\\core\\core.cpp.obj", "source\\deploy\\core\\core.cpp", "-imsvc", "D:\\Windows Kits\\10\\Include\\10.0.22621.0\\cppwinrt", "-imsvc", "D:\\Windows Kits\\10\\Include\\10.0.22621.0\\shared", "-imsvc", "D:\\Windows Kits\\10\\Include\\10.0.22621.0\\ucrt", "-imsvc", "D:\\Windows Kits\\10\\Include\\10.0.22621.0\\um", "-imsvc", "D:\\Windows Kits\\10\\Include\\10.0.22621.0\\winrt"],
  "file": "source\\deploy\\core\\core.cpp"
},
{
  "directory": "e:\\Projects\\Cpp\\TensorRT-YOLO",
  "arguments": ["D:\\laugh\\Program\\Microsoft Visual Studio\\2022\\Professional\\VC\\Tools\\MSVC\\14.38.33130\\bin\\HostX64\\x64\\cl.exe", "/c", "/nologo", "/O2", "/fp:fast", "/std:c++17", "/Ie:\\Projects\\Cpp\\TensorRT-YOLO\\include", "/IC:\\Program Files\\NVIDIA GPU Computing Toolkit\\TensorRT\\v8.6.1.6\\include", "/IC:\\Program Files\\NVIDIA GPU Computing Toolkit\\CUDA\\v11.7\\include", "/DENABLE_DEPLOY_BUILDING_DLL", "/EHsc", "/ID:\\laugh\\Program\\Xmake\\.xmake\\packages\\o\\opencv\\4.8.0\\69684747aed04b64833b165b90454f36\\include", "/DNDEBUG", "/Fobuild\\.objs\\deploy\\windows\\x64\\release\\source\\deploy\\core\\tensor.cpp.obj", "source\\deploy\\core\\tensor.cpp", "-imsvc", "D:\\Windows Kits\\10\\Include\\10.0.22621.0\\cppwinrt", "-imsvc", "D:\\Windows Kits\\10\\Include\\10.0.22621.0\\shared", "-imsvc", "D:\\Windows Kits\\10\\Include\\10.0.22621.0\\ucrt", "-imsvc", "D:\\Windows Kits\\10\\Include\\10.0.22621.0\\um", "-imsvc", "D:\\Windows Kits\\10\\Include\\10.0.22621.0\\winrt"],
  "file": "source\\deploy\\core\\tensor.cpp"
},
{
  "directory": "e:\\Projects\\Cpp\\TensorRT-YOLO",
  "arguments": ["D:\\laugh\\Program\\Microsoft Visual Studio\\2022\\Professional\\VC\\Tools\\MSVC\\14.38.33130\\bin\\HostX64\\x64\\cl.exe", "/c", "/nologo", "/O2", "/fp:fast", "/std:c++17", "/Ie:\\Projects\\Cpp\\TensorRT-YOLO\\include", "/IC:\\Program Files\\NVIDIA GPU Computing Toolkit\\TensorRT\\v8.6.1.6\\include", "/IC:\\Program Files\\NVIDIA GPU Computing Toolkit\\CUDA\\v11.7\\include", "/DENABLE_DEPLOY_BUILDING_DLL", "/EHsc", "/ID:\\laugh\\Program\\Xmake\\.xmake\\packages\\o\\opencv\\4.8.0\\69684747aed04b64833b165b90454f36\\include", "/DNDEBUG", "/Fobuild\\.objs\\deploy\\windows\\x64\\release\\source\\deploy\\core\\types.cpp.obj", "source\\deploy\\core\\types.cpp", "-imsvc", "D:\\Windows Kits\\10\\Include\\10.0.22621.0\\cppwinrt", "-imsvc", "D:\\Windows Kits\\10\\Include\\10.0.22621.0\\shared", "-imsvc", "D:\\Windows Kits\\10\\Include\\10.0.22621.0\\ucrt", "-imsvc", "D:\\Windows Kits\\10\\Include\\10.0.22621.0\\um", "-imsvc", "D:\\Windows Kits\\10\\Include\\10.0.22621.0\\winrt"],
  "file": "source\\deploy\\core\\types.cpp"
},
{
  "directory": "e:\\Projects\\Cpp\\TensorRT-YOLO",
  "arguments": ["D:\\laugh\\Program\\Microsoft Visual Studio\\2022\\Professional\\VC\\Tools\\MSVC\\14.38.33130\\bin\\HostX64\\x64\\cl.exe", "/c", "/nologo", "/O2", "/fp:fast", "/std:c++17", "/Ie:\\Projects\\Cpp\\TensorRT-YOLO\\include", "/IC:\\Program Files\\NVIDIA GPU Computing Toolkit\\TensorRT\\v8.6.1.6\\include", "/IC:\\Program Files\\NVIDIA GPU Computing Toolkit\\CUDA\\v11.7\\include", "/DENABLE_DEPLOY_BUILDING_DLL", "/EHsc", "/ID:\\laugh\\Program\\Xmake\\.xmake\\packages\\o\\opencv\\4.8.0\\69684747aed04b64833b165b90454f36\\include", "/DNDEBUG", "/Fobuild\\.objs\\deploy\\windows\\x64\\release\\source\\deploy\\utils\\utils.cpp.obj", "source\\deploy\\utils\\utils.cpp", "-imsvc", "D:\\Windows Kits\\10\\Include\\10.0.22621.0\\cppwinrt", "-imsvc", "D:\\Windows Kits\\10\\Include\\10.0.22621.0\\shared", "-imsvc", "D:\\Windows Kits\\10\\Include\\10.0.22621.0\\ucrt", "-imsvc", "D:\\Windows Kits\\10\\Include\\10.0.22621.0\\um", "-imsvc", "D:\\Windows Kits\\10\\Include\\10.0.22621.0\\winrt"],
  "file": "source\\deploy\\utils\\utils.cpp"
},
{
  "directory": "e:\\Projects\\Cpp\\TensorRT-YOLO",
  "arguments": ["D:\\laugh\\Program\\Microsoft Visual Studio\\2022\\Professional\\VC\\Tools\\MSVC\\14.38.33130\\bin\\HostX64\\x64\\cl.exe", "/c", "/nologo", "/O2", "/fp:fast", "/std:c++17", "/Ie:\\Projects\\Cpp\\TensorRT-YOLO\\include", "/IC:\\Program Files\\NVIDIA GPU Computing Toolkit\\TensorRT\\v8.6.1.6\\include", "/IC:\\Program Files\\NVIDIA GPU Computing Toolkit\\CUDA\\v11.7\\include", "/DENABLE_DEPLOY_BUILDING_DLL", "/EHsc", "/ID:\\laugh\\Program\\Xmake\\.xmake\\packages\\o\\opencv\\4.8.0\\69684747aed04b64833b165b90454f36\\include", "/DNDEBUG", "/Fobuild\\.objs\\deploy\\windows\\x64\\release\\source\\deploy\\vision\\detection.cpp.obj", "source\\deploy\\vision\\detection.cpp", "-imsvc", "D:\\Windows Kits\\10\\Include\\10.0.22621.0\\cppwinrt", "-imsvc", "D:\\Windows Kits\\10\\Include\\10.0.22621.0\\shared", "-imsvc", "D:\\Windows Kits\\10\\Include\\10.0.22621.0\\ucrt", "-imsvc", "D:\\Windows Kits\\10\\Include\\10.0.22621.0\\um", "-imsvc", "D:\\Windows Kits\\10\\Include\\10.0.22621.0\\winrt"],
  "file": "source\\deploy\\vision\\detection.cpp"
},
{
  "directory": "e:\\Projects\\Cpp\\TensorRT-YOLO",
  "arguments": ["D:\\laugh\\Program\\Microsoft Visual Studio\\2022\\Professional\\VC\\Tools\\MSVC\\14.38.33130\\bin\\HostX64\\x64\\cl.exe", "/c", "/nologo", "/O2", "/fp:fast", "/std:c++17", "/Ie:\\Projects\\Cpp\\TensorRT-YOLO\\include", "/IC:\\Program Files\\NVIDIA GPU Computing Toolkit\\TensorRT\\v8.6.1.6\\include", "/IC:\\Program Files\\NVIDIA GPU Computing Toolkit\\CUDA\\v11.7\\include", "/DENABLE_DEPLOY_BUILDING_DLL", "/EHsc", "/ID:\\laugh\\Program\\Xmake\\.xmake\\packages\\o\\opencv\\4.8.0\\69684747aed04b64833b165b90454f36\\include", "/DNDEBUG", "/Fobuild\\.objs\\deploy\\windows\\x64\\release\\source\\deploy\\vision\\visualize.cpp.obj", "source\\deploy\\vision\\visualize.cpp", "-imsvc", "D:\\Windows Kits\\10\\Include\\10.0.22621.0\\cppwinrt", "-imsvc", "D:\\Windows Kits\\10\\Include\\10.0.22621.0\\shared", "-imsvc", "D:\\Windows Kits\\10\\Include\\10.0.22621.0\\ucrt", "-imsvc", "D:\\Windows Kits\\10\\Include\\10.0.22621.0\\um", "-imsvc", "D:\\Windows Kits\\10\\Include\\10.0.22621.0\\winrt"],
  "file": "source\\deploy\\vision\\visualize.cpp"
}]
